Metadata-Version: 1.0
Name: py-rockyou
Version: 0.0.1
Summary: Brute force dictionary
Home-page: UNKNOWN
Author: dimorinny
Author-email: didika914@gmail.com
License: UNKNOWN
Platform: UNKNOWN
